Python_Lambda_Logistics-0.0.2b0.dist-info/METADATA
Python_Lambda_Logistics-0.0.2b0.dist-info/RECORD
Python_Lambda_Logistics-0.0.2b0.dist-info/WHEEL
Python_Lambda_Logistics-0.0.2b0.dist-info/top_level.txt
pll/__about__.py
pll/__init__.py
pll/__main__.py
pll/templates/cli.j2
