Metadata-Version: 2.1
Name: Python-Lambda-Logistics
Version: 0.0.2b0
Summary: Automation for Python 3 packaging and deployment on AWS Lambda
Home-page: https://github.com/darth-veitcher/python-lambda-logistics
Author: James Veitch
Author-email: james@jamesveitch.com
License: MIT
Keywords: python lambda local docker deploy compile
Platform: any
Classifier: Programming Language :: Python
Classifier: Development Status :: 4 - Beta
Classifier: Natural Language :: English
Classifier: Environment :: Web Environment
Classifier: Intended Audience :: Developers
Classifier: License :: OSI Approved :: MIT License
Classifier: Operating System :: OS Independent
Classifier: Topic :: Software Development :: Libraries :: Python Modules
Classifier: Programming Language :: Python :: 3.6
Requires-Python: >=3.6
Requires-Dist: pyaml
Requires-Dist: jinja2
